reservoirs_wflow/__init__.py
reservoirs_wflow/reservoirs.py
reservoirs_wflow/rules.py
reservoirs_wflow-0.4.dev0.dist-info/LICENSE
reservoirs_wflow-0.4.dev0.dist-info/METADATA
reservoirs_wflow-0.4.dev0.dist-info/WHEEL
reservoirs_wflow-0.4.dev0.dist-info/entry_points.txt
reservoirs_wflow-0.4.dev0.dist-info/top_level.txt
reservoirs_wflow-0.4.dev0.dist-info/RECORD
