Metadata-Version: 2.1
Name: reservoirs-wflow
Version: 0.4.dev0
Summary: Simulate Wflow-like reservoirs
Author-email: Sebastian Hartgring <sebastian.hartgring@deltares.nl>
License: MIT License
Project-URL: Source, https://github.com/shartgring/reservoirs_wflow
Project-URL: Wflow, https://github.com/Deltares/Wflow.jl/
Keywords: wflow,hydromt,reservoir
Classifier: License :: OSI Approved :: MIT License
Classifier: Programming Language :: Python
Classifier: Programming Language :: Python :: 3
Requires-Python: >=3.9
License-File: LICENSE
Requires-Dist: numpy
Requires-Dist: pandas
Provides-Extra: dev
Requires-Dist: hydromt ; extra == 'dev'
Requires-Dist: hydromt-wflow ; extra == 'dev'
